simpliqm/__init__.py
simpliqm/__main__.py
simpliqm/cli.py
simpliqm/minimize.py
simpliqm/term.py
simpliqm-1.0.0.dist-info/LICENSE
simpliqm-1.0.0.dist-info/METADATA
simpliqm-1.0.0.dist-info/WHEEL
simpliqm-1.0.0.dist-info/entry_points.txt
simpliqm-1.0.0.dist-info/top_level.txt
simpliqm-1.0.0.dist-info/RECORD
