Metadata-Version: 2.1
Name: simpliqm
Version: 1.0.0
Summary: A powerful tool for minimizing Boolean functions
Author-email: Daniel Copley <djcopley@users.noreply.github.com>
Project-URL: Homepage, https://github.com/djcopley/QuineMcCluskey
Project-URL: Repository, https://github.com/djcopley/QuineMcCluskey.git
Project-URL: Issues, https://github.com/djcopley/QuineMcCluskey/issues
Classifier: Development Status :: 5 - Production/Stable
Classifier: Operating System :: OS Independent
Classifier: Topic :: Scientific/Engineering :: Mathematics
Classifier: Programming Language :: Python :: 3
Classifier: Programming Language :: Python :: 3.6
Classifier: Programming Language :: Python :: 3.7
Classifier: Programming Language :: Python :: 3.8
Classifier: Programming Language :: Python :: 3.9
Classifier: Programming Language :: Python :: 3.10
Classifier: Programming Language :: Python :: 3.11
Classifier: Programming Language :: Python :: 3.12
Classifier: License :: OSI Approved :: GNU General Public License v3 (GPLv3)
Requires-Python: >=3.6
License-File: LICENSE
